task_arrange/__init__.py
task_arrange/core.py
task_arrange/database.py
task_arrange/delete/__init__.py
task_arrange/delete/main.py
task_arrange/delete/realLife__1.py
task_arrange/delete/task_func__1.py
task_arrange/delete/tasks.py
task_arrange/delete/utils.py
task_arrange/reallife/__init__.py
task_arrange/reallife/abstra.py
task_arrange/reallife/cli.py
task_arrange/reallife/core22.py
task_arrange/reallife/execution_strategy.py
task_arrange/reallife/workday_facade.py
task_arrange/server/mcp/__init__.py
task_arrange/server/mcp/prompt.py
task_arrange/server/router/__init__.py
task_arrange/server/router/prompt.py
task_arrange-0.1.2.dist-info/METADATA
task_arrange-0.1.2.dist-info/WHEEL
task_arrange-0.1.2.dist-info/top_level.txt
task_arrange-0.1.2.dist-info/RECORD
